README.md
setup.py
pulumi_flyio/__init__.py
pulumi_flyio/_utilities.py
pulumi_flyio/app.py
pulumi_flyio/certificate.py
pulumi_flyio/certificate_issuance_waiter.py
pulumi_flyio/get_app.py
pulumi_flyio/ip.py
pulumi_flyio/machine.py
pulumi_flyio/outputs.py
pulumi_flyio/postgres_attachment.py
pulumi_flyio/provider.py
pulumi_flyio/pulumi-plugin.json
pulumi_flyio/py.typed
pulumi_flyio/random.py
pulumi_flyio/secrets.py
pulumi_flyio/volume.py
pulumi_flyio/wire_guard_peer.py
pulumi_flyio/wire_guard_token.py
pulumi_flyio.egg-info/PKG-INFO
pulumi_flyio.egg-info/SOURCES.txt
pulumi_flyio.egg-info/dependency_links.txt
pulumi_flyio.egg-info/not-zip-safe
pulumi_flyio.egg-info/requires.txt
pulumi_flyio.egg-info/top_level.txt
pulumi_flyio/config/__init__.py
pulumi_flyio/config/__init__.pyi
pulumi_flyio/config/vars.py
pulumi_flyio/flyio/__init__.py
pulumi_flyio/flyio/_inputs.py
pulumi_flyio/flyio/outputs.py
pulumi_flyio/time/__init__.py
pulumi_flyio/time/outputs.py